herosdevices/__init__.py
herosdevices/helper.py
herosdevices/core/__init__.py
herosdevices/core/gpio.py
herosdevices/core/bus/__init__.py
herosdevices/core/bus/onewire.py
herosdevices/core/bus/serial.py
herosdevices/core/bus/visa.py
herosdevices/core/bus/telnet/__init__.py
herosdevices/core/bus/telnet/telnet.py
herosdevices/core/bus/telnet/telnetlib.py
herosdevices/core/templates/__init__.py
herosdevices/core/templates/acq_device.py
herosdevices/core/templates/camera.py
herosdevices/core/templates/display.py
herosdevices/core/templates/oscilloscope.py
herosdevices/core/templates/serial.py
herosdevices/core/templates/telnet.py
herosdevices/core/templates/visa.py
herosdevices/hardware/Ftdi.py
herosdevices/hardware/__init__.py
herosdevices/hardware/ftdi.py
herosdevices/hardware/gamma_vacuum.py
herosdevices/hardware/picotechnology.py
herosdevices/hardware/rigol.py
herosdevices/hardware/windfreak.py
herosdevices/hardware/analog_devices/__init__.py
herosdevices/hardware/analog_devices/ds18b20.py
herosdevices/hardware/dummy/__init__.py
herosdevices/hardware/dummy/cameras.py
herosdevices/hardware/dummy/displays.py
herosdevices/hardware/dummy/electronics.py
herosdevices/hardware/hamamatsu/__init__.py
herosdevices/hardware/hamamatsu/dcam_camera.py
herosdevices/hardware/highfinesse/__init__.py
herosdevices/hardware/highfinesse/wsx.py
herosdevices/hardware/ids/__init__.py
herosdevices/hardware/ids/peak_camera.py
herosdevices/hardware/raspberrypi/__init__.py
herosdevices/hardware/raspberrypi/dhtxx.py
herosdevices/hardware/raspberrypi/waveshare.py
herosdevices/hardware/raspberrypi/max318xx/__init__.py
herosdevices/hardware/raspberrypi/max318xx/max31855.py
herosdevices/hardware/raspberrypi/max318xx/max31865.py
herosdevices/hardware/raspberrypi/max318xx/max318xx.py
herosdevices/hardware/rohde_schwarz/__init__.py
herosdevices/hardware/rohde_schwarz/ngx.py
herosdevices/hardware/saes/__init__.py
herosdevices/hardware/saes/nextorr.py
herosdevices/hardware/santec/__init__.py
herosdevices-0.8.6.dist-info/METADATA
herosdevices-0.8.6.dist-info/WHEEL
herosdevices-0.8.6.dist-info/licenses/LICENSE
herosdevices-0.8.6.dist-info/RECORD
