Metadata-Version: 2.4
Name: herosdevices
Version: 0.8.6
Summary: Python representations (think drivers) of frequently used lab equipment.
Project-URL: Homepage, https://gitlab.com/atomiq-project/herosdevices
Project-URL: Repository, https://gitlab.com/atomiq-project/herosdevices
Project-URL: Bug Tracker, https://gitlab.com/atomiq-project/herosdevices/issues
Author-email: Thomas Niederprüm <t.niederpruem@rptu.de>, Suthep Pomjaksilp <suthep.pomjaksilp@uni-hamburg.de>, Christian Hölzl <choelzl@pi5.physik.uni-stuttgart.de>, Tobias Ebert <tobias.ebert@uni-hamburg.de>
Maintainer-email: Thomas Niederprüm <t.niederpruem@rptu.de>, Suthep Pomjaksilp <suthep.pomjaksilp@uni-hamburg.de>
License: LGPL-3.0-or-later
License-File: LICENSE
Keywords: pub/sub,remote object,rpc,zenoh
Classifier: Development Status :: 4 - Beta
Classifier: Environment :: Console
Classifier: Intended Audience :: Developers
Classifier: Intended Audience :: Science/Research
Classifier: License :: OSI Approved :: GNU Lesser General Public License v3 or later (LGPLv3+)
Classifier: Programming Language :: Python :: 3
Classifier: Programming Language :: Python :: 3 :: Only
Classifier: Programming Language :: Python :: 3.9
Classifier: Programming Language :: Python :: 3.10
Classifier: Programming Language :: Python :: 3.11
Classifier: Programming Language :: Python :: 3.12
Classifier: Programming Language :: Python :: 3.13
Classifier: Topic :: Communications
Requires-Python: >=3.10
Requires-Dist: ftd3xx
Requires-Dist: gpiod; sys_platform == 'linux'
Requires-Dist: heros>=0.7
Requires-Dist: pyftdi
Requires-Dist: pyserial
Requires-Dist: python-dateutil
Requires-Dist: pyvisa
Requires-Dist: pyvisa-py
Requires-Dist: spidev; sys_platform == 'linux'
Requires-Dist: toptica-lasersdk==3.2.0
Provides-Extra: dev
Requires-Dist: docstring-parser; extra == 'dev'
Requires-Dist: hatch; extra == 'dev'
Requires-Dist: mypy; extra == 'dev'
Requires-Dist: pre-commit>=4; extra == 'dev'
Requires-Dist: pytest-cov>=4.0; extra == 'dev'
Requires-Dist: pytest>=8; extra == 'dev'
Requires-Dist: ruff>=0.12; extra == 'dev'
Requires-Dist: types-pyserial; extra == 'dev'
Requires-Dist: types-python-dateutil; extra == 'dev'
Requires-Dist: types-rpi-gpio; extra == 'dev'
Provides-Extra: docs
Requires-Dist: docstring-parser; extra == 'docs'
Requires-Dist: furo>=2024; extra == 'docs'
Requires-Dist: hatch; extra == 'docs'
Requires-Dist: sphinx-argparse; extra == 'docs'
Requires-Dist: sphinx-autoapi>=3; extra == 'docs'
Requires-Dist: sphinx-autodoc-typehints>=3; (python_version >= '3.11') and extra == 'docs'
Requires-Dist: sphinx-copybutton; extra == 'docs'
Requires-Dist: sphinx-tabs; extra == 'docs'
Requires-Dist: sphinx<9,>=8; (python_version >= '3.11') and extra == 'docs'
Requires-Dist: toml; extra == 'docs'
Provides-Extra: rpi
Requires-Dist: adafruit-circuitpython-dht; extra == 'rpi'
Requires-Dist: gpiozero; extra == 'rpi'
Requires-Dist: lgpio; extra == 'rpi'
Requires-Dist: pigpio; extra == 'rpi'
Requires-Dist: rpi-gpio; extra == 'rpi'
